<con:messageContainer modelBaseVersion="3" xmlns:com="http://datex2.eu/schema/3/common" xmlns:d2="http://datex2.eu/schema/3/d2Payload" xmlns:ex="http://datex2.eu/schema/3/exchangeInformation" xmlns:loc="http://datex2.eu/schema/3/locationReferencing" xmlns:con="http://datex2.eu/schema/3/messageContainer" xmlns:roa="http://datex2.eu/schema/3/roadTrafficData" xmlns:sit="http://datex2.eu/schema/3/situation" xmlns:sta="http://datex2.eu/schema/3/staExtensions" xmlns:wd="http://datex2.eu/schema/3/weatherDataExtension" xmlns:xsi="http://www.w3.org/2001/XMLSchema-instance">
  <con:payload xsi:type="sit:SituationPublication" lang="sv" modelBaseVersion="3">
    <com:publicationTime>2025-10-24T13:20:11.000+02:00</com:publicationTime>
    <com:publicationCreator>
      <com:country>SE</com:country>
      <com:nationalIdentifier>STA</com:nationalIdentifier>
    </com:publicationCreator>
    <sit:situation id="e085403a-95e7-4686-a28a-2b8eefd0488f">
      <sit:overallSeverity>high</sit:overallSeverity>
      <sit:situationVersionTime>2025-09-11T08:48:31.693+02:00</sit:situationVersionTime>
      <sit:headerInformation>
        <com:confidentiality>noRestriction</com:confidentiality>
        <com:informationStatus>real</com:informationStatus>
      </sit:headerInformation>
      <sit:situationRecord xsi:type="sit:NonWeatherRelatedRoadConditions" id="SE_STA_TRISSID_1_7258162" version="4">
        <sit:situationRecordCreationTime>2025-07-10T14:32:48.913+02:00</sit:situationRecordCreationTime>
        <sit:situationRecordVersionTime>2025-09-11T08:48:31.693+02:00</sit:situationRecordVersionTime>
        <sit:situationRecordFirstSupplierVersionTime>2025-09-11T08:48:31.693+02:00</sit:situationRecordFirstSupplierVersionTime>
        <sit:probabilityOfOccurrence>certain</sit:probabilityOfOccurrence>
        <sit:severity>high</sit:severity>
        <sit:source>
          <com:sourceName>
            <com:values>
              <com:value lang="sv">Trafikverket</com:value>
            </com:values>
          </com:sourceName>
        </sit:source>
        <sit:validity>
          <com:validityStatus>definedByValidityTimeSpec</com:validityStatus>
          <com:validityTimeSpecification>
            <com:overallStartTime>2025-07-10T14:30:30.000+02:00</com:overallStartTime>
            <com:overallEndTime>2025-10-31T12:00:00.000+01:00</com:overallEndTime>
          </com:validityTimeSpecification>
        </sit:validity>
        <sit:impact>
          <sit:numberOfLanesRestricted>1</sit:numberOfLanesRestricted>
        </sit:impact>
        <sit:generalPublicComment>
          <sit:comment>
            <com:values>
              <com:value lang="sv">På grund av dålig bärighet på bron över Helgumsjön får trafiken passera växelvis över bron. Trafiken dirigeras med trafikljus. Sluttiden är preliminär.</com:value>
            </com:values>
          </sit:comment>
          <sit:commentType>description</sit:commentType>
        </sit:generalPublicComment>
        <sit:locationReference xsi:type="loc:LocationGroupByList">
          <loc:locationContainedInGroup xsi:type="loc:PointLocation">
            <loc:coordinatesForDisplay>
              <loc:latitude>63.15261</loc:latitude>
              <loc:longitude>16.956148</loc:longitude>
            </loc:coordinatesForDisplay>
            <loc:supplementaryPositionalDescription>
              <loc:lengthAffected>538</loc:lengthAffected>
              <loc:locationDescription>
                <com:values>
                  <com:value lang="sv">Väg 331 från Helgum till Östergransjö båda riktningarna i Västernorrlands län (Y)</com:value>
                </com:values>
              </loc:locationDescription>
              <loc:carriageway>
                <loc:carriageway>mainCarriageway</loc:carriageway>
              </loc:carriageway>
              <loc:namedArea xsi:type="loc:IsoNamedArea">
                <loc:areaName>
                  <com:values>
                    <com:value lang="sv">Saknas</com:value>
                  </com:values>
                </loc:areaName>
                <loc:country>SE</loc:country>
                <loc:subdivisionType>county</loc:subdivisionType>
                <loc:subdivisionCode>22</loc:subdivisionCode>
              </loc:namedArea>
              <loc:roadInformation>
                <loc:roadNumber>Väg 331</loc:roadNumber>
              </loc:roadInformation>
            </loc:supplementaryPositionalDescription>
            <loc:alertCPoint xsi:type="loc:AlertCMethod4Point">
              <loc:alertCLocationCountryCode>E</loc:alertCLocationCountryCode>
              <loc:alertCLocationTableNumber>33</loc:alertCLocationTableNumber>
              <loc:alertCLocationTableVersion>2.2</loc:alertCLocationTableVersion>
              <loc:alertCDirection>
                <loc:alertCDirectionCoded>negative</loc:alertCDirectionCoded>
                <loc:alertCAffectedDirection>both</loc:alertCAffectedDirection>
              </loc:alertCDirection>
              <loc:alertCMethod4PrimaryPointLocation>
                <loc:alertCLocation>
                  <loc:specificLocation>25105</loc:specificLocation>
                </loc:alertCLocation>
                <loc:offsetDistance>
                  <loc:offsetDistance>0</loc:offsetDistance>
                </loc:offsetDistance>
              </loc:alertCMethod4PrimaryPointLocation>
            </loc:alertCPoint>
          </loc:locationContainedInGroup>
          <loc:locationContainedInGroup xsi:type="loc:LinearLocation">
            <loc:coordinatesForDisplay>
              <loc:latitude>63.15261</loc:latitude>
              <loc:longitude>16.956148</loc:longitude>
            </loc:coordinatesForDisplay>
            <loc:supplementaryPositionalDescription>
              <loc:lengthAffected>538</loc:lengthAffected>
              <loc:locationDescription>
                <com:values>
                  <com:value lang="sv">Väg 331 från Helgum till Östergransjö båda riktningarna i Västernorrlands län (Y)</com:value>
                </com:values>
              </loc:locationDescription>
              <loc:carriageway>
                <loc:carriageway>mainCarriageway</loc:carriageway>
              </loc:carriageway>
              <loc:namedArea xsi:type="loc:IsoNamedArea">
                <loc:areaName>
                  <com:values>
                    <com:value lang="sv">Saknas</com:value>
                  </com:values>
                </loc:areaName>
                <loc:country>SE</loc:country>
                <loc:subdivisionType>county</loc:subdivisionType>
                <loc:subdivisionCode>22</loc:subdivisionCode>
              </loc:namedArea>
              <loc:roadInformation>
                <loc:roadNumber>Väg 331</loc:roadNumber>
              </loc:roadInformation>
            </loc:supplementaryPositionalDescription>
            <loc:openlrLinear>
              <loc:firstDirection>
                <loc:openlrLocationReferencePoint>
                  <loc:openlrCoordinates>
                    <loc:latitude>63.150543</loc:latitude>
                    <loc:longitude>16.959047</loc:longitude>
                  </loc:openlrCoordinates>
                  <loc:openlrLineAttributes>
                    <loc:openlrFunctionalRoadClass>frc3</loc:openlrFunctionalRoadClass>
                    <loc:openlrFormOfWay>undefined</loc:openlrFormOfWay>
                    <loc:openlrBearing>319</loc:openlrBearing>
                  </loc:openlrLineAttributes>
                  <loc:openlrPathAttributes>
                    <loc:openlrLowestFrcToNextLRPoint>frc3</loc:openlrLowestFrcToNextLRPoint>
                    <loc:openlrDistanceToNextLRPoint>212</loc:openlrDistanceToNextLRPoint>
                  </loc:openlrPathAttributes>
                </loc:openlrLocationReferencePoint>
                <loc:openlrLocationReferencePoint>
                  <loc:openlrCoordinates>
                    <loc:latitude>63.15212</loc:latitude>
                    <loc:longitude>16.956694</loc:longitude>
                  </loc:openlrCoordinates>
                  <loc:openlrLineAttributes>
                    <loc:openlrFunctionalRoadClass>frc3</loc:openlrFunctionalRoadClass>
                    <loc:openlrFormOfWay>undefined</loc:openlrFormOfWay>
                    <loc:openlrBearing>331</loc:openlrBearing>
                  </loc:openlrLineAttributes>
                  <loc:openlrPathAttributes>
                    <loc:openlrLowestFrcToNextLRPoint>frc3</loc:openlrLowestFrcToNextLRPoint>
                    <loc:openlrDistanceToNextLRPoint>331</loc:openlrDistanceToNextLRPoint>
                  </loc:openlrPathAttributes>
                </loc:openlrLocationReferencePoint>
                <loc:openlrLastLocationReferencePoint>
                  <loc:openlrCoordinates>
                    <loc:latitude>63.15484</loc:latitude>
                    <loc:longitude>16.95405</loc:longitude>
                  </loc:openlrCoordinates>
                  <loc:openlrLineAttributes>
                    <loc:openlrFunctionalRoadClass>frc3</loc:openlrFunctionalRoadClass>
                    <loc:openlrFormOfWay>undefined</loc:openlrFormOfWay>
                    <loc:openlrBearing>154</loc:openlrBearing>
                  </loc:openlrLineAttributes>
                </loc:openlrLastLocationReferencePoint>
                <loc:openlrOffsets>
                  <loc:openlrPositiveOffset>5</loc:openlrPositiveOffset>
                  <loc:openlrNegativeOffset>1</loc:openlrNegativeOffset>
                </loc:openlrOffsets>
              </loc:firstDirection>
              <loc:oppositeDirection>
                <loc:openlrLocationReferencePoint>
                  <loc:openlrCoordinates>
                    <loc:latitude>63.15484</loc:latitude>
                    <loc:longitude>16.95405</loc:longitude>
                  </loc:openlrCoordinates>
                  <loc:openlrLineAttributes>
                    <loc:openlrFunctionalRoadClass>frc3</loc:openlrFunctionalRoadClass>
                    <loc:openlrFormOfWay>undefined</loc:openlrFormOfWay>
                    <loc:openlrBearing>154</loc:openlrBearing>
                  </loc:openlrLineAttributes>
                  <loc:openlrPathAttributes>
                    <loc:openlrLowestFrcToNextLRPoint>frc3</loc:openlrLowestFrcToNextLRPoint>
                    <loc:openlrDistanceToNextLRPoint>331</loc:openlrDistanceToNextLRPoint>
                  </loc:openlrPathAttributes>
                </loc:openlrLocationReferencePoint>
                <loc:openlrLocationReferencePoint>
                  <loc:openlrCoordinates>
                    <loc:latitude>63.15212</loc:latitude>
                    <loc:longitude>16.956694</loc:longitude>
                  </loc:openlrCoordinates>
                  <loc:openlrLineAttributes>
                    <loc:openlrFunctionalRoadClass>frc3</loc:openlrFunctionalRoadClass>
                    <loc:openlrFormOfWay>undefined</loc:openlrFormOfWay>
                    <loc:openlrBearing>146</loc:openlrBearing>
                  </loc:openlrLineAttributes>
                  <loc:openlrPathAttributes>
                    <loc:openlrLowestFrcToNextLRPoint>frc3</loc:openlrLowestFrcToNextLRPoint>
                    <loc:openlrDistanceToNextLRPoint>212</loc:openlrDistanceToNextLRPoint>
                  </loc:openlrPathAttributes>
                </loc:openlrLocationReferencePoint>
                <loc:openlrLastLocationReferencePoint>
                  <loc:openlrCoordinates>
                    <loc:latitude>63.150543</loc:latitude>
                    <loc:longitude>16.959047</loc:longitude>
                  </loc:openlrCoordinates>
                  <loc:openlrLineAttributes>
                    <loc:openlrFunctionalRoadClass>frc3</loc:openlrFunctionalRoadClass>
                    <loc:openlrFormOfWay>undefined</loc:openlrFormOfWay>
                    <loc:openlrBearing>319</loc:openlrBearing>
                  </loc:openlrLineAttributes>
                </loc:openlrLastLocationReferencePoint>
                <loc:openlrOffsets>
                  <loc:openlrPositiveOffset>1</loc:openlrPositiveOffset>
                  <loc:openlrNegativeOffset>5</loc:openlrNegativeOffset>
                </loc:openlrOffsets>
              </loc:oppositeDirection>
            </loc:openlrLinear>
            <loc:gmlLineString>
              <loc:posList>16.958971757760104 63.150578368842837 16.958461476880931 63.150874149479876 16.956692896903938 63.152117240884479 16.955367628583023 63.153356447005621 16.954610639764716 63.154270796045033 16.954054107751187 63.154833758559519</loc:posList>
            </loc:gmlLineString>
          </loc:locationContainedInGroup>
        </sit:locationReference>
        <sit:nonWeatherRelatedRoadConditionType>roadSurfaceInPoorCondition</sit:nonWeatherRelatedRoadConditionType>
      </sit:situationRecord>
    </sit:situation>
    <sit:situation id="ea0013be-1b6e-4abd-81c6-e88dd06daae6">
      <sit:overallSeverity>low</sit:overallSeverity>
      <sit:situationVersionTime>2025-10-14T16:26:23.510+02:00</sit:situationVersionTime>
      <sit:headerInformation>
        <com:confidentiality>noRestriction</com:confidentiality>
        <com:informationStatus>real</com:informationStatus>
      </sit:headerInformation>
      <sit:situationRecord xsi:type="sit:GeneralObstruction" id="SE_STA_TRISSID_1_7348262" version="7">
        <sit:situationRecordCreationTime>2025-08-31T21:37:35.390+02:00</sit:situationRecordCreationTime>
        <sit:situationRecordVersionTime>2025-10-14T16:26:23.510+02:00</sit:situationRecordVersionTime>
        <sit:situationRecordFirstSupplierVersionTime>2025-10-14T16:26:23.510+02:00</sit:situationRecordFirstSupplierVersionTime>
        <sit:probabilityOfOccurrence>certain</sit:probabilityOfOccurrence>
        <sit:severity>low</sit:severity>
        <sit:source>
          <com:sourceName>
            <com:values>
              <com:value lang="sv">Trafikverket</com:value>
            </com:values>
          </com:sourceName>
        </sit:source>
        <sit:validity>
          <com:validityStatus>definedByValidityTimeSpec</com:validityStatus>
          <com:validityTimeSpecification>
            <com:overallStartTime>2025-08-31T21:36:46.000+02:00</com:overallStartTime>
            <com:overallEndTime>2025-11-15T15:00:00.000+01:00</com:overallEndTime>
          </com:validityTimeSpecification>
        </sit:validity>
        <sit:generalPublicComment>
          <sit:comment>
            <com:values>
              <com:value lang="sv">På grund av vägras på E6 i Norge så uppmanas trafikanter som ska åka in i Norge att besöka www.vegvesen.no för att planera sin färdväg. </com:value>
            </com:values>
          </sit:comment>
          <sit:commentType>description</sit:commentType>
        </sit:generalPublicComment>
        <sit:locationReference xsi:type="loc:LocationGroupByList">
          <loc:locationContainedInGroup xsi:type="loc:PointLocation">
            <loc:coordinatesForDisplay>
              <loc:latitude>63.649063</loc:latitude>
              <loc:longitude>12.259214</loc:longitude>
            </loc:coordinatesForDisplay>
            <loc:supplementaryPositionalDescription>
              <loc:locationDescription>
                <com:values>
                  <com:value lang="sv">Väg 322 vid Riksgräns SE/NO vid Sandvika båda riktningarna i Jämtlands län (Z)</com:value>
                </com:values>
              </loc:locationDescription>
              <loc:carriageway>
                <loc:carriageway>mainCarriageway</loc:carriageway>
              </loc:carriageway>
              <loc:namedArea xsi:type="loc:IsoNamedArea">
                <loc:areaName>
                  <com:values>
                    <com:value lang="sv">Saknas</com:value>
                  </com:values>
                </loc:areaName>
                <loc:country>SE</loc:country>
                <loc:subdivisionType>county</loc:subdivisionType>
                <loc:subdivisionCode>23</loc:subdivisionCode>
              </loc:namedArea>
              <loc:roadInformation>
                <loc:roadNumber>Väg 322</loc:roadNumber>
              </loc:roadInformation>
            </loc:supplementaryPositionalDescription>
            <loc:alertCPoint xsi:type="loc:AlertCMethod4Point">
              <loc:alertCLocationCountryCode>E</loc:alertCLocationCountryCode>
              <loc:alertCLocationTableNumber>33</loc:alertCLocationTableNumber>
              <loc:alertCLocationTableVersion>2.2</loc:alertCLocationTableVersion>
              <loc:alertCDirection>
                <loc:alertCDirectionCoded>negative</loc:alertCDirectionCoded>
                <loc:alertCAffectedDirection>both</loc:alertCAffectedDirection>
              </loc:alertCDirection>
              <loc:alertCMethod4PrimaryPointLocation>
                <loc:alertCLocation>
                  <loc:specificLocation>5868</loc:specificLocation>
                </loc:alertCLocation>
                <loc:offsetDistance>
                  <loc:offsetDistance>2</loc:offsetDistance>
                </loc:offsetDistance>
              </loc:alertCMethod4PrimaryPointLocation>
            </loc:alertCPoint>
          </loc:locationContainedInGroup>
          <loc:locationContainedInGroup xsi:type="loc:LinearLocation">
            <loc:coordinatesForDisplay>
              <loc:latitude>63.649063</loc:latitude>
              <loc:longitude>12.259214</loc:longitude>
            </loc:coordinatesForDisplay>
            <loc:supplementaryPositionalDescription>
              <loc:locationDescription>
                <com:values>
                  <com:value lang="sv">Väg 322 vid Riksgräns SE/NO vid Sandvika båda riktningarna i Jämtlands län (Z)</com:value>
                </com:values>
              </loc:locationDescription>
              <loc:carriageway>
                <loc:carriageway>mainCarriageway</loc:carriageway>
              </loc:carriageway>
              <loc:namedArea xsi:type="loc:IsoNamedArea">
                <loc:areaName>
                  <com:values>
                    <com:value lang="sv">Saknas</com:value>
                  </com:values>
                </loc:areaName>
                <loc:country>SE</loc:country>
                <loc:subdivisionType>county</loc:subdivisionType>
                <loc:subdivisionCode>23</loc:subdivisionCode>
              </loc:namedArea>
              <loc:roadInformation>
                <loc:roadNumber>Väg 322</loc:roadNumber>
              </loc:roadInformation>
            </loc:supplementaryPositionalDescription>
            <loc:openlrLinear>
              <loc:firstDirection>
                <loc:openlrLocationReferencePoint>
                  <loc:openlrCoordinates>
                    <loc:latitude>63.647736</loc:latitude>
                    <loc:longitude>12.262177</loc:longitude>
                  </loc:openlrCoordinates>
                  <loc:openlrLineAttributes>
                    <loc:openlrFunctionalRoadClass>frc3</loc:openlrFunctionalRoadClass>
                    <loc:openlrFormOfWay>undefined</loc:openlrFormOfWay>
                    <loc:openlrBearing>34</loc:openlrBearing>
                  </loc:openlrLineAttributes>
                  <loc:openlrPathAttributes>
                    <loc:openlrLowestFrcToNextLRPoint>frc3</loc:openlrLowestFrcToNextLRPoint>
                    <loc:openlrDistanceToNextLRPoint>408</loc:openlrDistanceToNextLRPoint>
                  </loc:openlrPathAttributes>
                </loc:openlrLocationReferencePoint>
                <loc:openlrLastLocationReferencePoint>
                  <loc:openlrCoordinates>
                    <loc:latitude>63.649067</loc:latitude>
                    <loc:longitude>12.259164</loc:longitude>
                  </loc:openlrCoordinates>
                  <loc:openlrLineAttributes>
                    <loc:openlrFunctionalRoadClass>frc3</loc:openlrFunctionalRoadClass>
                    <loc:openlrFormOfWay>undefined</loc:openlrFormOfWay>
                    <loc:openlrBearing>110</loc:openlrBearing>
                  </loc:openlrLineAttributes>
                </loc:openlrLastLocationReferencePoint>
                <loc:openlrOffsets>
                  <loc:openlrPositiveOffset>403</loc:openlrPositiveOffset>
                  <loc:openlrNegativeOffset>5</loc:openlrNegativeOffset>
                </loc:openlrOffsets>
              </loc:firstDirection>
              <loc:oppositeDirection>
                <loc:openlrLocationReferencePoint>
                  <loc:openlrCoordinates>
                    <loc:latitude>63.649067</loc:latitude>
                    <loc:longitude>12.259164</loc:longitude>
                  </loc:openlrCoordinates>
                  <loc:openlrLineAttributes>
                    <loc:openlrFunctionalRoadClass>frc3</loc:openlrFunctionalRoadClass>
                    <loc:openlrFormOfWay>undefined</loc:openlrFormOfWay>
                    <loc:openlrBearing>110</loc:openlrBearing>
                  </loc:openlrLineAttributes>
                  <loc:openlrPathAttributes>
                    <loc:openlrLowestFrcToNextLRPoint>frc3</loc:openlrLowestFrcToNextLRPoint>
                    <loc:openlrDistanceToNextLRPoint>408</loc:openlrDistanceToNextLRPoint>
                  </loc:openlrPathAttributes>
                </loc:openlrLocationReferencePoint>
                <loc:openlrLastLocationReferencePoint>
                  <loc:openlrCoordinates>
                    <loc:latitude>63.647736</loc:latitude>
                    <loc:longitude>12.262177</loc:longitude>
                  </loc:openlrCoordinates>
                  <loc:openlrLineAttributes>
                    <loc:openlrFunctionalRoadClass>frc3</loc:openlrFunctionalRoadClass>
                    <loc:openlrFormOfWay>undefined</loc:openlrFormOfWay>
                    <loc:openlrBearing>34</loc:openlrBearing>
                  </loc:openlrLineAttributes>
                </loc:openlrLastLocationReferencePoint>
                <loc:openlrOffsets>
                  <loc:openlrPositiveOffset>5</loc:openlrPositiveOffset>
                  <loc:openlrNegativeOffset>403</loc:openlrNegativeOffset>
                </loc:openlrOffsets>
              </loc:oppositeDirection>
            </loc:openlrLinear>
            <loc:gmlLineString>
              <loc:posList>12.259214060330196 63.649061349279641 12.259164262687628 63.649068572240267</loc:posList>
            </loc:gmlLineString>
          </loc:locationContainedInGroup>
        </sit:locationReference>
        <sit:obstructionType>obstructionOnTheRoad</sit:obstructionType>
      </sit:situationRecord>
    </sit:situation>
    <sit:situation id="eb1850d2-3d7b-4f66-ade8-77e34a4cfbd4">
      <sit:overallSeverity>low</sit:overallSeverity>
      <sit:situationVersionTime>2025-10-14T16:26:53.590+02:00</sit:situationVersionTime>
      <sit:headerInformation>
        <com:confidentiality>noRestriction</com:confidentiality>
        <com:informationStatus>real</com:informationStatus>
      </sit:headerInformation>
      <sit:situationRecord xsi:type="sit:GeneralObstruction" id="SE_STA_TRISSID_1_7348282" version="6">
        <sit:situationRecordCreationTime>2025-08-31T21:37:36.930+02:00</sit:situationRecordCreationTime>
        <sit:situationRecordVersionTime>2025-10-14T16:26:53.590+02:00</sit:situationRecordVersionTime>
        <sit:situationRecordFirstSupplierVersionTime>2025-10-14T16:26:53.590+02:00</sit:situationRecordFirstSupplierVersionTime>
        <sit:probabilityOfOccurrence>certain</sit:probabilityOfOccurrence>
        <sit:severity>low</sit:severity>
        <sit:source>
          <com:sourceName>
            <com:values>
              <com:value lang="sv">Trafikverket</com:value>
            </com:values>
          </com:sourceName>
        </sit:source>
        <sit:validity>
          <com:validityStatus>definedByValidityTimeSpec</com:validityStatus>
          <com:validityTimeSpecification>
            <com:overallStartTime>2025-08-31T21:37:14.000+02:00</com:overallStartTime>
            <com:overallEndTime>2025-11-15T15:00:00.000+01:00</com:overallEndTime>
          </com:validityTimeSpecification>
        </sit:validity>
        <sit:generalPublicComment>
          <sit:comment>
            <com:values>
              <com:value lang="sv">På grund av vägras på E6 i Norge så uppmanas trafikanter som ska åka in i Norge att besöka www.vegvesen.no för att planera sin färdväg. </com:value>
            </com:values>
          </sit:comment>
          <sit:commentType>description</sit:commentType>
        </sit:generalPublicComment>
        <sit:locationReference xsi:type="loc:LocationGroupByList">
          <loc:locationContainedInGroup xsi:type="loc:PointLocation">
            <loc:coordinatesForDisplay>
              <loc:latitude>63.336227</loc:latitude>
              <loc:longitude>12.059452</loc:longitude>
            </loc:coordinatesForDisplay>
            <loc:supplementaryPositionalDescription>
              <loc:lengthAffected>1</loc:lengthAffected>
              <loc:locationDescription>
                <com:values>
                  <com:value lang="sv">E14 vid Riksgräns SE/NO vid Teveldalen båda riktningarna i Jämtlands län (Z)</com:value>
                </com:values>
              </loc:locationDescription>
              <loc:carriageway>
                <loc:carriageway>mainCarriageway</loc:carriageway>
              </loc:carriageway>
              <loc:namedArea xsi:type="loc:IsoNamedArea">
                <loc:areaName>
                  <com:values>
                    <com:value lang="sv">Saknas</com:value>
                  </com:values>
                </loc:areaName>
                <loc:country>SE</loc:country>
                <loc:subdivisionType>county</loc:subdivisionType>
                <loc:subdivisionCode>23</loc:subdivisionCode>
              </loc:namedArea>
              <loc:roadInformation>
                <loc:roadNumber>E14</loc:roadNumber>
              </loc:roadInformation>
            </loc:supplementaryPositionalDescription>
            <loc:alertCPoint xsi:type="loc:AlertCMethod4Point">
              <loc:alertCLocationCountryCode>E</loc:alertCLocationCountryCode>
              <loc:alertCLocationTableNumber>33</loc:alertCLocationTableNumber>
              <loc:alertCLocationTableVersion>2.2</loc:alertCLocationTableVersion>
              <loc:alertCDirection>
                <loc:alertCDirectionCoded>negative</loc:alertCDirectionCoded>
                <loc:alertCAffectedDirection>both</loc:alertCAffectedDirection>
              </loc:alertCDirection>
              <loc:alertCMethod4PrimaryPointLocation>
                <loc:alertCLocation>
                  <loc:specificLocation>5617</loc:specificLocation>
                </loc:alertCLocation>
                <loc:offsetDistance>
                  <loc:offsetDistance>2</loc:offsetDistance>
                </loc:offsetDistance>
              </loc:alertCMethod4PrimaryPointLocation>
            </loc:alertCPoint>
          </loc:locationContainedInGroup>
          <loc:locationContainedInGroup xsi:type="loc:LinearLocation">
            <loc:coordinatesForDisplay>
              <loc:latitude>63.336227</loc:latitude>
              <loc:longitude>12.059452</loc:longitude>
            </loc:coordinatesForDisplay>
            <loc:supplementaryPositionalDescription>
              <loc:lengthAffected>1</loc:lengthAffected>
              <loc:locationDescription>
                <com:values>
                  <com:value lang="sv">E14 vid Riksgräns SE/NO vid Teveldalen båda riktningarna i Jämtlands län (Z)</com:value>
                </com:values>
              </loc:locationDescription>
              <loc:carriageway>
                <loc:carriageway>mainCarriageway</loc:carriageway>
              </loc:carriageway>
              <loc:namedArea xsi:type="loc:IsoNamedArea">
                <loc:areaName>
                  <com:values>
                    <com:value lang="sv">Saknas</com:value>
                  </com:values>
                </loc:areaName>
                <loc:country>SE</loc:country>
                <loc:subdivisionType>county</loc:subdivisionType>
                <loc:subdivisionCode>23</loc:subdivisionCode>
              </loc:namedArea>
              <loc:roadInformation>
                <loc:roadNumber>E14</loc:roadNumber>
              </loc:roadInformation>
            </loc:supplementaryPositionalDescription>
            <loc:openlrLinear>
              <loc:firstDirection>
                <loc:openlrLocationReferencePoint>
                  <loc:openlrCoordinates>
                    <loc:latitude>63.335407</loc:latitude>
                    <loc:longitude>12.061217</loc:longitude>
                  </loc:openlrCoordinates>
                  <loc:openlrLineAttributes>
                    <loc:openlrFunctionalRoadClass>frc0</loc:openlrFunctionalRoadClass>
                    <loc:openlrFormOfWay>undefined</loc:openlrFormOfWay>
                    <loc:openlrBearing>327</loc:openlrBearing>
                  </loc:openlrLineAttributes>
                  <loc:openlrPathAttributes>
                    <loc:openlrLowestFrcToNextLRPoint>frc0</loc:openlrLowestFrcToNextLRPoint>
                    <loc:openlrDistanceToNextLRPoint>131</loc:openlrDistanceToNextLRPoint>
                  </loc:openlrPathAttributes>
                </loc:openlrLocationReferencePoint>
                <loc:openlrLastLocationReferencePoint>
                  <loc:openlrCoordinates>
                    <loc:latitude>63.336254</loc:latitude>
                    <loc:longitude>12.059412</loc:longitude>
                  </loc:openlrCoordinates>
                  <loc:openlrLineAttributes>
                    <loc:openlrFunctionalRoadClass>frc0</loc:openlrFunctionalRoadClass>
                    <loc:openlrFormOfWay>undefined</loc:openlrFormOfWay>
                    <loc:openlrBearing>136</loc:openlrBearing>
                  </loc:openlrLineAttributes>
                </loc:openlrLastLocationReferencePoint>
                <loc:openlrOffsets>
                  <loc:openlrPositiveOffset>127</loc:openlrPositiveOffset>
                  <loc:openlrNegativeOffset>4</loc:openlrNegativeOffset>
                </loc:openlrOffsets>
              </loc:firstDirection>
              <loc:oppositeDirection>
                <loc:openlrLocationReferencePoint>
                  <loc:openlrCoordinates>
                    <loc:latitude>63.336254</loc:latitude>
                    <loc:longitude>12.059412</loc:longitude>
                  </loc:openlrCoordinates>
                  <loc:openlrLineAttributes>
                    <loc:openlrFunctionalRoadClass>frc0</loc:openlrFunctionalRoadClass>
                    <loc:openlrFormOfWay>undefined</loc:openlrFormOfWay>
                    <loc:openlrBearing>136</loc:openlrBearing>
                  </loc:openlrLineAttributes>
                  <loc:openlrPathAttributes>
                    <loc:openlrLowestFrcToNextLRPoint>frc0</loc:openlrLowestFrcToNextLRPoint>
                    <loc:openlrDistanceToNextLRPoint>131</loc:openlrDistanceToNextLRPoint>
                  </loc:openlrPathAttributes>
                </loc:openlrLocationReferencePoint>
                <loc:openlrLastLocationReferencePoint>
                  <loc:openlrCoordinates>
                    <loc:latitude>63.335407</loc:latitude>
                    <loc:longitude>12.061217</loc:longitude>
                  </loc:openlrCoordinates>
                  <loc:openlrLineAttributes>
                    <loc:openlrFunctionalRoadClass>frc0</loc:openlrFunctionalRoadClass>
                    <loc:openlrFormOfWay>undefined</loc:openlrFormOfWay>
                    <loc:openlrBearing>327</loc:openlrBearing>
                  </loc:openlrLineAttributes>
                </loc:openlrLastLocationReferencePoint>
                <loc:openlrOffsets>
                  <loc:openlrPositiveOffset>4</loc:openlrPositiveOffset>
                  <loc:openlrNegativeOffset>127</loc:openlrNegativeOffset>
                </loc:openlrOffsets>
              </loc:oppositeDirection>
            </loc:openlrLinear>
            <loc:gmlLineString>
              <loc:posList>12.059469873345163 63.336230456572061 12.05945692077244 63.336235937819936</loc:posList>
            </loc:gmlLineString>
          </loc:locationContainedInGroup>
        </sit:locationReference>
        <sit:obstructionType>obstructionOnTheRoad</sit:obstructionType>
      </sit:situationRecord>
    </sit:situation>
    <sit:situation id="f2ef549f-8bbf-4002-988c-828e8bd0a37f">
      <sit:overallSeverity>low</sit:overallSeverity>
      <sit:situationVersionTime>2025-10-14T16:26:03.653+02:00</sit:situationVersionTime>
      <sit:headerInformation>
        <com:confidentiality>noRestriction</com:confidentiality>
        <com:informationStatus>real</com:informationStatus>
      </sit:headerInformation>
      <sit:situationRecord xsi:type="sit:GeneralObstruction" id="SE_STA_TRISSID_1_7348242" version="8">
        <sit:situationRecordCreationTime>2025-08-31T21:37:31.710+02:00</sit:situationRecordCreationTime>
        <sit:situationRecordVersionTime>2025-10-14T16:26:03.653+02:00</sit:situationRecordVersionTime>
        <sit:situationRecordFirstSupplierVersionTime>2025-10-14T16:26:03.653+02:00</sit:situationRecordFirstSupplierVersionTime>
        <sit:probabilityOfOccurrence>certain</sit:probabilityOfOccurrence>
        <sit:severity>low</sit:severity>
        <sit:source>
          <com:sourceName>
            <com:values>
              <com:value lang="sv">Trafikverket</com:value>
            </com:values>
          </com:sourceName>
        </sit:source>
        <sit:validity>
          <com:validityStatus>definedByValidityTimeSpec</com:validityStatus>
          <com:validityTimeSpecification>
            <com:overallStartTime>2025-08-31T21:31:01.000+02:00</com:overallStartTime>
            <com:overallEndTime>2025-11-15T15:00:00.000+01:00</com:overallEndTime>
          </com:validityTimeSpecification>
        </sit:validity>
        <sit:generalPublicComment>
          <sit:comment>
            <com:values>
              <com:value lang="sv">På grund av vägras på E6 i Norge så uppmanas trafikanter som ska åka in i Norge att besöka www.vegvesen.no för att planera sin färdväg. </com:value>
            </com:values>
          </sit:comment>
          <sit:commentType>description</sit:commentType>
        </sit:generalPublicComment>
        <sit:locationReference xsi:type="loc:PointLocation">
          <loc:coordinatesForDisplay>
            <loc:latitude>63.68839</loc:latitude>
            <loc:longitude>12.311383</loc:longitude>
          </loc:coordinatesForDisplay>
          <loc:supplementaryPositionalDescription>
            <loc:locationDescription>
              <com:values>
                <com:value lang="sv">Väg 336 vid Riksgräns SE/NO vid Finnsjön båda riktningarna i Jämtlands län (Z)</com:value>
              </com:values>
            </loc:locationDescription>
            <loc:carriageway>
              <loc:carriageway>mainCarriageway</loc:carriageway>
            </loc:carriageway>
            <loc:namedArea xsi:type="loc:IsoNamedArea">
              <loc:areaName>
                <com:values>
                  <com:value lang="sv">Saknas</com:value>
                </com:values>
              </loc:areaName>
              <loc:country>SE</loc:country>
              <loc:subdivisionType>county</loc:subdivisionType>
              <loc:subdivisionCode>23</loc:subdivisionCode>
            </loc:namedArea>
          </loc:supplementaryPositionalDescription>
        </sit:locationReference>
        <sit:obstructionType>obstructionOnTheRoad</sit:obstructionType>
      </sit:situationRecord>
    </sit:situation>
    <sit:situation id="ff163bed-33fe-4996-9b8f-1ea2250dea34">
      <sit:overallSeverity>low</sit:overallSeverity>
      <sit:situationVersionTime>2025-10-13T12:06:37.677+02:00</sit:situationVersionTime>
      <sit:headerInformation>
        <com:confidentiality>noRestriction</com:confidentiality>
        <com:informationStatus>real</com:informationStatus>
      </sit:headerInformation>
      <sit:situationRecord xsi:type="sit:NonWeatherRelatedRoadConditions" id="SE_STA_TRISSID_1_7363482" version="9">
        <sit:situationRecordCreationTime>2025-09-08T14:29:10.110+02:00</sit:situationRecordCreationTime>
        <sit:situationRecordVersionTime>2025-10-13T12:06:37.677+02:00</sit:situationRecordVersionTime>
        <sit:situationRecordFirstSupplierVersionTime>2025-10-13T12:06:37.677+02:00</sit:situationRecordFirstSupplierVersionTime>
        <sit:probabilityOfOccurrence>certain</sit:probabilityOfOccurrence>
        <sit:severity>low</sit:severity>
        <sit:source>
          <com:sourceName>
            <com:values>
              <com:value lang="sv">Trafikverket</com:value>
            </com:values>
          </com:sourceName>
        </sit:source>
        <sit:validity>
          <com:validityStatus>definedByValidityTimeSpec</com:validityStatus>
          <com:validityTimeSpecification>
            <com:overallStartTime>2025-09-08T14:26:49.000+02:00</com:overallStartTime>
            <com:overallEndTime>2025-12-01T12:00:00.000+01:00</com:overallEndTime>
          </com:validityTimeSpecification>
        </sit:validity>
        <sit:impact>
          <sit:numberOfLanesRestricted>1</sit:numberOfLanesRestricted>
        </sit:impact>
        <sit:generalPublicComment>
          <sit:comment>
            <com:values>
              <com:value lang="sv">Vägtrumma som rasat i höjd med Pellbo. Körplåtar finns på plats.</com:value>
            </com:values>
          </sit:comment>
          <sit:commentType>description</sit:commentType>
        </sit:generalPublicComment>
        <sit:locationReference xsi:type="loc:LinearLocation">
          <loc:coordinatesForDisplay>
            <loc:latitude>60.186802</loc:latitude>
            <loc:longitude>16.355852</loc:longitude>
          </loc:coordinatesForDisplay>
          <loc:supplementaryPositionalDescription>
            <loc:lengthAffected>377</loc:lengthAffected>
            <loc:locationDescription>
              <com:values>
                <com:value lang="sv">Väg 708 från Backa till Högsveden båda riktningarna i Dalarnas Län (W)</com:value>
              </com:values>
            </loc:locationDescription>
            <loc:carriageway>
              <loc:carriageway>mainCarriageway</loc:carriageway>
            </loc:carriageway>
            <loc:namedArea xsi:type="loc:IsoNamedArea">
              <loc:areaName>
                <com:values>
                  <com:value lang="sv">Saknas</com:value>
                </com:values>
              </loc:areaName>
              <loc:country>SE</loc:country>
              <loc:subdivisionType>county</loc:subdivisionType>
              <loc:subdivisionCode>20</loc:subdivisionCode>
            </loc:namedArea>
            <loc:roadInformation>
              <loc:roadNumber>Väg 708</loc:roadNumber>
            </loc:roadInformation>
          </loc:supplementaryPositionalDescription>
          <loc:openlrLinear>
            <loc:firstDirection>
              <loc:openlrLocationReferencePoint>
                <loc:openlrCoordinates>
                  <loc:latitude>60.182938</loc:latitude>
                  <loc:longitude>16.35358</loc:longitude>
                </loc:openlrCoordinates>
                <loc:openlrLineAttributes>
                  <loc:openlrFunctionalRoadClass>frc5</loc:openlrFunctionalRoadClass>
                  <loc:openlrFormOfWay>undefined</loc:openlrFormOfWay>
                  <loc:openlrBearing>23</loc:openlrBearing>
                </loc:openlrLineAttributes>
                <loc:openlrPathAttributes>
                  <loc:openlrLowestFrcToNextLRPoint>frc5</loc:openlrLowestFrcToNextLRPoint>
                  <loc:openlrDistanceToNextLRPoint>655</loc:openlrDistanceToNextLRPoint>
                </loc:openlrPathAttributes>
              </loc:openlrLocationReferencePoint>
              <loc:openlrLastLocationReferencePoint>
                <loc:openlrCoordinates>
                  <loc:latitude>60.187515</loc:latitude>
                  <loc:longitude>16.353184</loc:longitude>
                </loc:openlrCoordinates>
                <loc:openlrLineAttributes>
                  <loc:openlrFunctionalRoadClass>frc5</loc:openlrFunctionalRoadClass>
                  <loc:openlrFormOfWay>undefined</loc:openlrFormOfWay>
                  <loc:openlrBearing>100</loc:openlrBearing>
                </loc:openlrLineAttributes>
              </loc:openlrLastLocationReferencePoint>
              <loc:openlrOffsets>
                <loc:openlrPositiveOffset>277</loc:openlrPositiveOffset>
                <loc:openlrNegativeOffset>2</loc:openlrNegativeOffset>
              </loc:openlrOffsets>
            </loc:firstDirection>
            <loc:oppositeDirection>
              <loc:openlrLocationReferencePoint>
                <loc:openlrCoordinates>
                  <loc:latitude>60.187515</loc:latitude>
                  <loc:longitude>16.353184</loc:longitude>
                </loc:openlrCoordinates>
                <loc:openlrLineAttributes>
                  <loc:openlrFunctionalRoadClass>frc5</loc:openlrFunctionalRoadClass>
                  <loc:openlrFormOfWay>undefined</loc:openlrFormOfWay>
                  <loc:openlrBearing>100</loc:openlrBearing>
                </loc:openlrLineAttributes>
                <loc:openlrPathAttributes>
                  <loc:openlrLowestFrcToNextLRPoint>frc5</loc:openlrLowestFrcToNextLRPoint>
                  <loc:openlrDistanceToNextLRPoint>655</loc:openlrDistanceToNextLRPoint>
                </loc:openlrPathAttributes>
              </loc:openlrLocationReferencePoint>
              <loc:openlrLastLocationReferencePoint>
                <loc:openlrCoordinates>
                  <loc:latitude>60.182938</loc:latitude>
                  <loc:longitude>16.35358</loc:longitude>
                </loc:openlrCoordinates>
                <loc:openlrLineAttributes>
                  <loc:openlrFunctionalRoadClass>frc5</loc:openlrFunctionalRoadClass>
                  <loc:openlrFormOfWay>undefined</loc:openlrFormOfWay>
                  <loc:openlrBearing>23</loc:openlrBearing>
                </loc:openlrLineAttributes>
              </loc:openlrLastLocationReferencePoint>
              <loc:openlrOffsets>
                <loc:openlrPositiveOffset>2</loc:openlrPositiveOffset>
                <loc:openlrNegativeOffset>277</loc:openlrNegativeOffset>
              </loc:openlrOffsets>
            </loc:oppositeDirection>
          </loc:openlrLinear>
          <loc:gmlLineString>
            <loc:posList>16.355362908729717 60.185144288083883 16.355383722747419 60.185242409340525 16.355845918047031 60.186275444194877 16.355869391916602 60.186809710270886 16.355823827850983 60.187021033165337 16.355719473113634 60.187122948841129 16.355469177860137 60.1872497951254 16.355081204979356 60.187335212286726 16.353184274019576 60.187513627933505</loc:posList>
          </loc:gmlLineString>
        </sit:locationReference>
        <sit:nonWeatherRelatedRoadConditionType>roadSurfaceInPoorCondition</sit:nonWeatherRelatedRoadConditionType>
      </sit:situationRecord>
    </sit:situation>
    <sit:situation id="65a8b47a-0d17-41ab-9511-1c92784bf496">
      <sit:overallSeverity>low</sit:overallSeverity>
      <sit:situationVersionTime>2025-09-26T11:58:07.713+02:00</sit:situationVersionTime>
      <sit:headerInformation>
        <com:confidentiality>noRestriction</com:confidentiality>
        <com:informationStatus>real</com:informationStatus>
      </sit:headerInformation>
      <sit:situationRecord xsi:type="sit:EquipmentOrSystemFault" id="SE_STA_TRISSID_1_22972259" version="5">
        <sit:situationRecordCreationTime>2025-09-19T10:01:32.890+02:00</sit:situationRecordCreationTime>
        <sit:situationRecordVersionTime>2025-09-26T11:58:07.713+02:00</sit:situationRecordVersionTime>
        <sit:situationRecordFirstSupplierVersionTime>2025-09-26T11:58:07.713+02:00</sit:situationRecordFirstSupplierVersionTime>
        <sit:probabilityOfOccurrence>certain</sit:probabilityOfOccurrence>
        <sit:severity>low</sit:severity>
        <sit:source>
          <com:sourceName>
            <com:values>
              <com:value lang="sv">Trafikverket</com:value>
            </com:values>
          </com:sourceName>
        </sit:source>
        <sit:validity>
          <com:validityStatus>definedByValidityTimeSpec</com:validityStatus>
          <com:validityTimeSpecification>
            <com:overallStartTime>2025-09-19T10:00:32.000+02:00</com:overallStartTime>
            <com:overallEndTime>2025-11-14T08:00:00.000+01:00</com:overallEndTime>
          </com:validityTimeSpecification>
        </sit:validity>
        <sit:generalPublicComment>
          <sit:comment>
            <com:values>
              <com:value lang="sv">Intervallfel på trafiksignalerna, felsökning pågår. Prognosen är preliminär och kan komma att ändras. </com:value>
            </com:values>
          </sit:comment>
          <sit:commentType>description</sit:commentType>
        </sit:generalPublicComment>
        <sit:locationReference xsi:type="loc:LocationGroupByList">
          <loc:locationContainedInGroup xsi:type="loc:PointLocation">
            <loc:coordinatesForDisplay>
              <loc:latitude>59.233517</loc:latitude>
              <loc:longitude>18.193077</loc:longitude>
            </loc:coordinatesForDisplay>
            <loc:supplementaryPositionalDescription>
              <loc:lengthAffected>11</loc:lengthAffected>
              <loc:locationDescription>
                <com:values>
                  <com:value lang="sv">Väg 260 vid Skrubba Malmväg  i Stockholms län (AB)</com:value>
                </com:values>
              </loc:locationDescription>
              <loc:carriageway>
                <loc:carriageway>mainCarriageway</loc:carriageway>
              </loc:carriageway>
              <loc:namedArea xsi:type="loc:IsoNamedArea">
                <loc:areaName>
                  <com:values>
                    <com:value lang="sv">Saknas</com:value>
                  </com:values>
                </loc:areaName>
                <loc:country>SE</loc:country>
                <loc:subdivisionType>county</loc:subdivisionType>
                <loc:subdivisionCode>2</loc:subdivisionCode>
              </loc:namedArea>
              <loc:roadInformation>
                <loc:roadName>Gudöbroleden</loc:roadName>
                <loc:roadNumber>Väg 260</loc:roadNumber>
              </loc:roadInformation>
            </loc:supplementaryPositionalDescription>
            <loc:alertCPoint xsi:type="loc:AlertCMethod4Point">
              <loc:alertCLocationCountryCode>E</loc:alertCLocationCountryCode>
              <loc:alertCLocationTableNumber>33</loc:alertCLocationTableNumber>
              <loc:alertCLocationTableVersion>2.2</loc:alertCLocationTableVersion>
              <loc:alertCDirection>
                <loc:alertCDirectionCoded>negative</loc:alertCDirectionCoded>
                <loc:alertCAffectedDirection>both</loc:alertCAffectedDirection>
              </loc:alertCDirection>
              <loc:alertCMethod4PrimaryPointLocation>
                <loc:alertCLocation>
                  <loc:specificLocation>4973</loc:specificLocation>
                </loc:alertCLocation>
                <loc:offsetDistance>
                  <loc:offsetDistance>0</loc:offsetDistance>
                </loc:offsetDistance>
              </loc:alertCMethod4PrimaryPointLocation>
            </loc:alertCPoint>
          </loc:locationContainedInGroup>
          <loc:locationContainedInGroup xsi:type="loc:LinearLocation">
            <loc:coordinatesForDisplay>
              <loc:latitude>59.233517</loc:latitude>
              <loc:longitude>18.193077</loc:longitude>
            </loc:coordinatesForDisplay>
            <loc:supplementaryPositionalDescription>
              <loc:lengthAffected>11</loc:lengthAffected>
              <loc:locationDescription>
                <com:values>
                  <com:value lang="sv">Väg 260 vid Skrubba Malmväg  i Stockholms län (AB)</com:value>
                </com:values>
              </loc:locationDescription>
              <loc:carriageway>
                <loc:carriageway>mainCarriageway</loc:carriageway>
              </loc:carriageway>
              <loc:namedArea xsi:type="loc:IsoNamedArea">
                <loc:areaName>
                  <com:values>
                    <com:value lang="sv">Saknas</com:value>
                  </com:values>
                </loc:areaName>
                <loc:country>SE</loc:country>
                <loc:subdivisionType>county</loc:subdivisionType>
                <loc:subdivisionCode>2</loc:subdivisionCode>
              </loc:namedArea>
              <loc:roadInformation>
                <loc:roadName>Gudöbroleden</loc:roadName>
                <loc:roadNumber>Väg 260</loc:roadNumber>
              </loc:roadInformation>
            </loc:supplementaryPositionalDescription>
            <loc:openlrLinear>
              <loc:firstDirection>
                <loc:openlrLocationReferencePoint>
                  <loc:openlrCoordinates>
                    <loc:latitude>59.233425</loc:latitude>
                    <loc:longitude>18.193262</loc:longitude>
                  </loc:openlrCoordinates>
                  <loc:openlrLineAttributes>
                    <loc:openlrFunctionalRoadClass>frc3</loc:openlrFunctionalRoadClass>
                    <loc:openlrFormOfWay>undefined</loc:openlrFormOfWay>
                    <loc:openlrBearing>316</loc:openlrBearing>
                  </loc:openlrLineAttributes>
                  <loc:openlrPathAttributes>
                    <loc:openlrLowestFrcToNextLRPoint>frc3</loc:openlrLowestFrcToNextLRPoint>
                    <loc:openlrDistanceToNextLRPoint>181</loc:openlrDistanceToNextLRPoint>
                  </loc:openlrPathAttributes>
                </loc:openlrLocationReferencePoint>
                <loc:openlrLastLocationReferencePoint>
                  <loc:openlrCoordinates>
                    <loc:latitude>59.234688</loc:latitude>
                    <loc:longitude>18.191265</loc:longitude>
                  </loc:openlrCoordinates>
                  <loc:openlrLineAttributes>
                    <loc:openlrFunctionalRoadClass>frc3</loc:openlrFunctionalRoadClass>
                    <loc:openlrFormOfWay>undefined</loc:openlrFormOfWay>
                    <loc:openlrBearing>141</loc:openlrBearing>
                  </loc:openlrLineAttributes>
                </loc:openlrLastLocationReferencePoint>
                <loc:openlrOffsets>
                  <loc:openlrPositiveOffset>12</loc:openlrPositiveOffset>
                  <loc:openlrNegativeOffset>158</loc:openlrNegativeOffset>
                </loc:openlrOffsets>
              </loc:firstDirection>
              <loc:oppositeDirection>
                <loc:openlrLocationReferencePoint>
                  <loc:openlrCoordinates>
                    <loc:latitude>59.234688</loc:latitude>
                    <loc:longitude>18.191265</loc:longitude>
                  </loc:openlrCoordinates>
                  <loc:openlrLineAttributes>
                    <loc:openlrFunctionalRoadClass>frc3</loc:openlrFunctionalRoadClass>
                    <loc:openlrFormOfWay>undefined</loc:openlrFormOfWay>
                    <loc:openlrBearing>141</loc:openlrBearing>
                  </loc:openlrLineAttributes>
                  <loc:openlrPathAttributes>
                    <loc:openlrLowestFrcToNextLRPoint>frc3</loc:openlrLowestFrcToNextLRPoint>
                    <loc:openlrDistanceToNextLRPoint>181</loc:openlrDistanceToNextLRPoint>
                  </loc:openlrPathAttributes>
                </loc:openlrLocationReferencePoint>
                <loc:openlrLastLocationReferencePoint>
                  <loc:openlrCoordinates>
                    <loc:latitude>59.233425</loc:latitude>
                    <loc:longitude>18.193262</loc:longitude>
                  </loc:openlrCoordinates>
                  <loc:openlrLineAttributes>
                    <loc:openlrFunctionalRoadClass>frc3</loc:openlrFunctionalRoadClass>
                    <loc:openlrFormOfWay>undefined</loc:openlrFormOfWay>
                    <loc:openlrBearing>316</loc:openlrBearing>
                  </loc:openlrLineAttributes>
                </loc:openlrLastLocationReferencePoint>
                <loc:openlrOffsets>
                  <loc:openlrPositiveOffset>158</loc:openlrPositiveOffset>
                  <loc:openlrNegativeOffset>12</loc:openlrNegativeOffset>
                </loc:openlrOffsets>
              </loc:oppositeDirection>
            </loc:openlrLinear>
            <loc:gmlLineString>
              <loc:posList>18.193164006773333 59.233483052896808 18.193023069188158 59.233566229437059 18.193020428972147 59.23356800181655</loc:posList>
            </loc:gmlLineString>
          </loc:locationContainedInGroup>
        </sit:locationReference>
        <sit:equipmentOrSystemFaultType>notWorking</sit:equipmentOrSystemFaultType>
        <sit:faultyEquipmentOrSystemType>trafficSignals</sit:faultyEquipmentOrSystemType>
      </sit:situationRecord>
    </sit:situation>
    <sit:situation id="74726166-696b-656e-6e75-000000003356">
      <sit:overallSeverity>low</sit:overallSeverity>
      <sit:situationVersionTime>2025-10-07T10:30:08.157+02:00</sit:situationVersionTime>
      <sit:headerInformation>
        <com:confidentiality>noRestriction</com:confidentiality>
        <com:informationStatus>real</com:informationStatus>
      </sit:headerInformation>
      <sit:situationRecord xsi:type="sit:GeneralObstruction" id="SE_STA_TRISSID_1_6866721" version="1">
        <sit:situationRecordCreationTime>2025-10-07T10:30:08.157+02:00</sit:situationRecordCreationTime>
        <sit:situationRecordVersionTime>2025-10-07T10:30:08.157+02:00</sit:situationRecordVersionTime>
        <sit:situationRecordFirstSupplierVersionTime>2025-10-07T10:30:08.157+02:00</sit:situationRecordFirstSupplierVersionTime>
        <sit:probabilityOfOccurrence>certain</sit:probabilityOfOccurrence>
        <sit:severity>low</sit:severity>
        <sit:source>
          <com:sourceName>
            <com:values>
              <com:value lang="sv">Trollhättans stad</com:value>
            </com:values>
          </com:sourceName>
        </sit:source>
        <sit:validity>
          <com:validityStatus>definedByValidityTimeSpec</com:validityStatus>
          <com:validityTimeSpecification>
            <com:overallStartTime>2025-10-27T07:00:00.000+01:00</com:overallStartTime>
            <com:overallEndTime>2025-10-31T16:00:00.000+01:00</com:overallEndTime>
          </com:validityTimeSpecification>
        </sit:validity>
        <sit:generalPublicComment>
          <sit:comment>
            <com:values>
              <com:value lang="sv">Trädbeskärning och schakt nära gångbana och körbana.</com:value>
            </com:values>
          </sit:comment>
          <sit:commentType>description</sit:commentType>
        </sit:generalPublicComment>
        <sit:locationReference xsi:type="loc:LinearLocation">
          <loc:coordinatesForDisplay>
            <loc:latitude>58.28515</loc:latitude>
            <loc:longitude>12.309333</loc:longitude>
          </loc:coordinatesForDisplay>
          <loc:supplementaryPositionalDescription>
            <loc:locationDescription>
              <com:values>
                <com:value lang="sv">Peter Baggegatan i Trollhättans kommun i Västra Götalands län, i båda riktningar.</com:value>
              </com:values>
            </loc:locationDescription>
            <loc:carriageway>
              <loc:carriageway>mainCarriageway</loc:carriageway>
            </loc:carriageway>
            <loc:namedArea xsi:type="loc:IsoNamedArea">
              <loc:areaName>
                <com:values>
                  <com:value lang="sv">Saknas</com:value>
                </com:values>
              </loc:areaName>
              <loc:country>SE</loc:country>
              <loc:subdivisionType>county</loc:subdivisionType>
              <loc:subdivisionCode>14</loc:subdivisionCode>
            </loc:namedArea>
            <loc:roadInformation>
              <loc:roadName>Peter Baggegatan</loc:roadName>
            </loc:roadInformation>
          </loc:supplementaryPositionalDescription>
          <loc:openlrLinear>
            <loc:firstDirection>
              <loc:openlrLocationReferencePoint>
                <loc:openlrCoordinates>
                  <loc:latitude>58.284748</loc:latitude>
                  <loc:longitude>12.308651</loc:longitude>
                </loc:openlrCoordinates>
                <loc:openlrLineAttributes>
                  <loc:openlrFunctionalRoadClass>frc7</loc:openlrFunctionalRoadClass>
                  <loc:openlrFormOfWay>undefined</loc:openlrFormOfWay>
                  <loc:openlrBearing>31</loc:openlrBearing>
                </loc:openlrLineAttributes>
                <loc:openlrPathAttributes>
                  <loc:openlrLowestFrcToNextLRPoint>frc7</loc:openlrLowestFrcToNextLRPoint>
                  <loc:openlrDistanceToNextLRPoint>276</loc:openlrDistanceToNextLRPoint>
                </loc:openlrPathAttributes>
              </loc:openlrLocationReferencePoint>
              <loc:openlrLastLocationReferencePoint>
                <loc:openlrCoordinates>
                  <loc:latitude>58.286552</loc:latitude>
                  <loc:longitude>12.311832</loc:longitude>
                </loc:openlrCoordinates>
                <loc:openlrLineAttributes>
                  <loc:openlrFunctionalRoadClass>frc7</loc:openlrFunctionalRoadClass>
                  <loc:openlrFormOfWay>undefined</loc:openlrFormOfWay>
                  <loc:openlrBearing>225</loc:openlrBearing>
                </loc:openlrLineAttributes>
              </loc:openlrLastLocationReferencePoint>
              <loc:openlrOffsets>
                <loc:openlrPositiveOffset>62</loc:openlrPositiveOffset>
                <loc:openlrNegativeOffset>214</loc:openlrNegativeOffset>
              </loc:openlrOffsets>
            </loc:firstDirection>
            <loc:oppositeDirection>
              <loc:openlrLocationReferencePoint>
                <loc:openlrCoordinates>
                  <loc:latitude>58.286552</loc:latitude>
                  <loc:longitude>12.311832</loc:longitude>
                </loc:openlrCoordinates>
                <loc:openlrLineAttributes>
                  <loc:openlrFunctionalRoadClass>frc7</loc:openlrFunctionalRoadClass>
                  <loc:openlrFormOfWay>undefined</loc:openlrFormOfWay>
                  <loc:openlrBearing>225</loc:openlrBearing>
                </loc:openlrLineAttributes>
                <loc:openlrPathAttributes>
                  <loc:openlrLowestFrcToNextLRPoint>frc7</loc:openlrLowestFrcToNextLRPoint>
                  <loc:openlrDistanceToNextLRPoint>276</loc:openlrDistanceToNextLRPoint>
                </loc:openlrPathAttributes>
              </loc:openlrLocationReferencePoint>
              <loc:openlrLastLocationReferencePoint>
                <loc:openlrCoordinates>
                  <loc:latitude>58.284748</loc:latitude>
                  <loc:longitude>12.308651</loc:longitude>
                </loc:openlrCoordinates>
                <loc:openlrLineAttributes>
                  <loc:openlrFunctionalRoadClass>frc7</loc:openlrFunctionalRoadClass>
                  <loc:openlrFormOfWay>undefined</loc:openlrFormOfWay>
                  <loc:openlrBearing>31</loc:openlrBearing>
                </loc:openlrLineAttributes>
              </loc:openlrLastLocationReferencePoint>
              <loc:openlrOffsets>
                <loc:openlrPositiveOffset>214</loc:openlrPositiveOffset>
                <loc:openlrNegativeOffset>62</loc:openlrNegativeOffset>
              </loc:openlrOffsets>
            </loc:oppositeDirection>
          </loc:openlrLinear>
          <loc:gmlLineString>
            <loc:posList>12.309332576439743 58.285147934420834 12.309560037952471 58.285275742936221</loc:posList>
          </loc:gmlLineString>
        </sit:locationReference>
        <sit:obstructionType>obstructionOnTheRoad</sit:obstructionType>
      </sit:situationRecord>
    </sit:situation>
    <sit:situation id="74726166-696b-656e-6e75-000000003357">
      <sit:overallSeverity>highest</sit:overallSeverity>
      <sit:situationVersionTime>2025-10-07T13:05:37.023+02:00</sit:situationVersionTime>
      <sit:headerInformation>
        <com:confidentiality>noRestriction</com:confidentiality>
        <com:informationStatus>real</com:informationStatus>
      </sit:headerInformation>
      <sit:situationRecord xsi:type="sit:PublicEvent" id="SE_STA_TRISSID_1_6870201" version="1">
        <sit:situationRecordCreationTime>2025-10-07T13:05:37.023+02:00</sit:situationRecordCreationTime>
        <sit:situationRecordVersionTime>2025-10-07T13:05:37.023+02:00</sit:situationRecordVersionTime>
        <sit:situationRecordFirstSupplierVersionTime>2025-10-07T13:05:37.023+02:00</sit:situationRecordFirstSupplierVersionTime>
        <sit:probabilityOfOccurrence>certain</sit:probabilityOfOccurrence>
        <sit:severity>highest</sit:severity>
        <sit:source>
          <com:sourceName>
            <com:values>
              <com:value lang="sv">Kungälvs kommun</com:value>
            </com:values>
          </com:sourceName>
        </sit:source>
        <sit:validity>
          <com:validityStatus>definedByValidityTimeSpec</com:validityStatus>
          <com:validityTimeSpecification>
            <com:overallStartTime>2025-10-24T07:00:00.000+02:00</com:overallStartTime>
            <com:overallEndTime>2025-10-24T18:00:00.000+02:00</com:overallEndTime>
          </com:validityTimeSpecification>
        </sit:validity>
        <sit:generalPublicComment>
          <sit:comment>
            <com:values>
              <com:value lang="sv">Ytterbyvägen stängs av för all motordriven trafik den 24 oktober då det skall vara marknad.Detta är från Bäckvägen upp till cirkulationen vida stadshuset (Strandgatan/ Uddevallavägen) och det kommer vara helt avstängt mellan 08:00-18:00</com:value>
            </com:values>
          </sit:comment>
          <sit:commentType>description</sit:commentType>
        </sit:generalPublicComment>
        <sit:locationReference xsi:type="loc:LinearLocation">
          <loc:coordinatesForDisplay>
            <loc:latitude>57.870728</loc:latitude>
            <loc:longitude>11.97942</loc:longitude>
          </loc:coordinatesForDisplay>
          <loc:supplementaryPositionalDescription>
            <loc:locationDescription>
              <com:values>
                <com:value lang="sv">Ytterbyvägen i Kungälvs kommun i Västra Götalands län, i båda riktningar.</com:value>
              </com:values>
            </loc:locationDescription>
            <loc:carriageway>
              <loc:carriageway>mainCarriageway</loc:carriageway>
            </loc:carriageway>
            <loc:namedArea xsi:type="loc:IsoNamedArea">
              <loc:areaName>
                <com:values>
                  <com:value lang="sv">Saknas</com:value>
                </com:values>
              </loc:areaName>
              <loc:country>SE</loc:country>
              <loc:subdivisionType>county</loc:subdivisionType>
              <loc:subdivisionCode>14</loc:subdivisionCode>
            </loc:namedArea>
            <loc:roadInformation>
              <loc:roadName>Ytterbyvägen</loc:roadName>
            </loc:roadInformation>
          </loc:supplementaryPositionalDescription>
          <loc:openlrLinear>
            <loc:firstDirection>
              <loc:openlrLocationReferencePoint>
                <loc:openlrCoordinates>
                  <loc:latitude>57.87074</loc:latitude>
                  <loc:longitude>11.979612</loc:longitude>
                </loc:openlrCoordinates>
                <loc:openlrLineAttributes>
                  <loc:openlrFunctionalRoadClass>frc5</loc:openlrFunctionalRoadClass>
                  <loc:openlrFormOfWay>undefined</loc:openlrFormOfWay>
                  <loc:openlrBearing>267</loc:openlrBearing>
                </loc:openlrLineAttributes>
                <loc:openlrPathAttributes>
                  <loc:openlrLowestFrcToNextLRPoint>frc5</loc:openlrLowestFrcToNextLRPoint>
                  <loc:openlrDistanceToNextLRPoint>74</loc:openlrDistanceToNextLRPoint>
                </loc:openlrPathAttributes>
              </loc:openlrLocationReferencePoint>
              <loc:openlrLastLocationReferencePoint>
                <loc:openlrCoordinates>
                  <loc:latitude>57.87067</loc:latitude>
                  <loc:longitude>11.978363</loc:longitude>
                </loc:openlrCoordinates>
                <loc:openlrLineAttributes>
                  <loc:openlrFunctionalRoadClass>frc5</loc:openlrFunctionalRoadClass>
                  <loc:openlrFormOfWay>undefined</loc:openlrFormOfWay>
                  <loc:openlrBearing>87</loc:openlrBearing>
                </loc:openlrLineAttributes>
              </loc:openlrLastLocationReferencePoint>
              <loc:openlrOffsets>
                <loc:openlrPositiveOffset>11</loc:openlrPositiveOffset>
                <loc:openlrNegativeOffset>62</loc:openlrNegativeOffset>
              </loc:openlrOffsets>
            </loc:firstDirection>
            <loc:oppositeDirection>
              <loc:openlrLocationReferencePoint>
                <loc:openlrCoordinates>
                  <loc:latitude>57.87067</loc:latitude>
                  <loc:longitude>11.978363</loc:longitude>
                </loc:openlrCoordinates>
                <loc:openlrLineAttributes>
                  <loc:openlrFunctionalRoadClass>frc5</loc:openlrFunctionalRoadClass>
                  <loc:openlrFormOfWay>undefined</loc:openlrFormOfWay>
                  <loc:openlrBearing>87</loc:openlrBearing>
                </loc:openlrLineAttributes>
                <loc:openlrPathAttributes>
                  <loc:openlrLowestFrcToNextLRPoint>frc5</loc:openlrLowestFrcToNextLRPoint>
                  <loc:openlrDistanceToNextLRPoint>74</loc:openlrDistanceToNextLRPoint>
                </loc:openlrPathAttributes>
              </loc:openlrLocationReferencePoint>
              <loc:openlrLastLocationReferencePoint>
                <loc:openlrCoordinates>
                  <loc:latitude>57.87074</loc:latitude>
                  <loc:longitude>11.979612</loc:longitude>
                </loc:openlrCoordinates>
                <loc:openlrLineAttributes>
                  <loc:openlrFunctionalRoadClass>frc5</loc:openlrFunctionalRoadClass>
                  <loc:openlrFormOfWay>undefined</loc:openlrFormOfWay>
                  <loc:openlrBearing>267</loc:openlrBearing>
                </loc:openlrLineAttributes>
              </loc:openlrLastLocationReferencePoint>
              <loc:openlrOffsets>
                <loc:openlrPositiveOffset>62</loc:openlrPositiveOffset>
                <loc:openlrNegativeOffset>11</loc:openlrNegativeOffset>
              </loc:openlrOffsets>
            </loc:oppositeDirection>
          </loc:openlrLinear>
          <loc:gmlLineString>
            <loc:posList>11.979419257369411 57.870728956501175 11.979088162110786 57.870710736523655</loc:posList>
          </loc:gmlLineString>
        </sit:locationReference>
        <sit:publicEventType>majorEvent</sit:publicEventType>
      </sit:situationRecord>
      <sit:situationRecord xsi:type="sit:RoadOrCarriagewayOrLaneManagement" id="SE_STA_TRISSID_2_6870201" version="1">
        <sit:situationRecordCreationTime>2025-10-07T13:05:37.023+02:00</sit:situationRecordCreationTime>
        <sit:situationRecordVersionTime>2025-10-07T13:05:37.023+02:00</sit:situationRecordVersionTime>
        <sit:situationRecordFirstSupplierVersionTime>2025-10-07T13:05:37.023+02:00</sit:situationRecordFirstSupplierVersionTime>
        <sit:probabilityOfOccurrence>certain</sit:probabilityOfOccurrence>
        <sit:severity>highest</sit:severity>
        <sit:source>
          <com:sourceName>
            <com:values>
              <com:value lang="sv">Kungälvs kommun</com:value>
            </com:values>
          </com:sourceName>
        </sit:source>
        <sit:validity>
          <com:validityStatus>definedByValidityTimeSpec</com:validityStatus>
          <com:validityTimeSpecification>
            <com:overallStartTime>2025-10-24T07:00:00.000+02:00</com:overallStartTime>
            <com:overallEndTime>2025-10-24T18:00:00.000+02:00</com:overallEndTime>
          </com:validityTimeSpecification>
        </sit:validity>
        <sit:cause>
          <sit:managedCause>
            <sit:objectReference targetClass="sit:SituationRecord" id="SE_STA_TRISSID_1_6870201" version="0"></sit:objectReference>
          </sit:managedCause>
        </sit:cause>
        <sit:generalPublicComment>
          <sit:comment>
            <com:values>
              <com:value lang="sv">Ytterbyvägen stängs av för all motordriven trafik den 24 oktober då det skall vara marknad.Detta är från Bäckvägen upp till cirkulationen vida stadshuset (Strandgatan/ Uddevallavägen) och det kommer vara helt avstängt mellan 08:00-18:00</com:value>
            </com:values>
          </sit:comment>
          <sit:commentType>description</sit:commentType>
        </sit:generalPublicComment>
        <sit:locationReference xsi:type="loc:LinearLocation">
          <loc:coordinatesForDisplay>
            <loc:latitude>57.870728</loc:latitude>
            <loc:longitude>11.97942</loc:longitude>
          </loc:coordinatesForDisplay>
          <loc:supplementaryPositionalDescription>
            <loc:locationDescription>
              <com:values>
                <com:value lang="sv">Ytterbyvägen i Kungälvs kommun i Västra Götalands län, i båda riktningar.</com:value>
              </com:values>
            </loc:locationDescription>
            <loc:carriageway>
              <loc:carriageway>mainCarriageway</loc:carriageway>
            </loc:carriageway>
            <loc:namedArea xsi:type="loc:IsoNamedArea">
              <loc:areaName>
                <com:values>
                  <com:value lang="sv">Saknas</com:value>
                </com:values>
              </loc:areaName>
              <loc:country>SE</loc:country>
              <loc:subdivisionType>county</loc:subdivisionType>
              <loc:subdivisionCode>14</loc:subdivisionCode>
            </loc:namedArea>
            <loc:roadInformation>
              <loc:roadName>Ytterbyvägen</loc:roadName>
            </loc:roadInformation>
          </loc:supplementaryPositionalDescription>
          <loc:openlrLinear>
            <loc:firstDirection>
              <loc:openlrLocationReferencePoint>
                <loc:openlrCoordinates>
                  <loc:latitude>57.87074</loc:latitude>
                  <loc:longitude>11.979612</loc:longitude>
                </loc:openlrCoordinates>
                <loc:openlrLineAttributes>
                  <loc:openlrFunctionalRoadClass>frc5</loc:openlrFunctionalRoadClass>
                  <loc:openlrFormOfWay>undefined</loc:openlrFormOfWay>
                  <loc:openlrBearing>267</loc:openlrBearing>
                </loc:openlrLineAttributes>
                <loc:openlrPathAttributes>
                  <loc:openlrLowestFrcToNextLRPoint>frc5</loc:openlrLowestFrcToNextLRPoint>
                  <loc:openlrDistanceToNextLRPoint>74</loc:openlrDistanceToNextLRPoint>
                </loc:openlrPathAttributes>
              </loc:openlrLocationReferencePoint>
              <loc:openlrLastLocationReferencePoint>
                <loc:openlrCoordinates>
                  <loc:latitude>57.87067</loc:latitude>
                  <loc:longitude>11.978363</loc:longitude>
                </loc:openlrCoordinates>
                <loc:openlrLineAttributes>
                  <loc:openlrFunctionalRoadClass>frc5</loc:openlrFunctionalRoadClass>
                  <loc:openlrFormOfWay>undefined</loc:openlrFormOfWay>
                  <loc:openlrBearing>87</loc:openlrBearing>
                </loc:openlrLineAttributes>
              </loc:openlrLastLocationReferencePoint>
              <loc:openlrOffsets>
                <loc:openlrPositiveOffset>11</loc:openlrPositiveOffset>
                <loc:openlrNegativeOffset>62</loc:openlrNegativeOffset>
              </loc:openlrOffsets>
            </loc:firstDirection>
            <loc:oppositeDirection>
              <loc:openlrLocationReferencePoint>
                <loc:openlrCoordinates>
                  <loc:latitude>57.87067</loc:latitude>
                  <loc:longitude>11.978363</loc:longitude>
                </loc:openlrCoordinates>
                <loc:openlrLineAttributes>
                  <loc:openlrFunctionalRoadClass>frc5</loc:openlrFunctionalRoadClass>
                  <loc:openlrFormOfWay>undefined</loc:openlrFormOfWay>
                  <loc:openlrBearing>87</loc:openlrBearing>
                </loc:openlrLineAttributes>
                <loc:openlrPathAttributes>
                  <loc:openlrLowestFrcToNextLRPoint>frc5</loc:openlrLowestFrcToNextLRPoint>
                  <loc:openlrDistanceToNextLRPoint>74</loc:openlrDistanceToNextLRPoint>
                </loc:openlrPathAttributes>
              </loc:openlrLocationReferencePoint>
              <loc:openlrLastLocationReferencePoint>
                <loc:openlrCoordinates>
                  <loc:latitude>57.87074</loc:latitude>
                  <loc:longitude>11.979612</loc:longitude>
                </loc:openlrCoordinates>
                <loc:openlrLineAttributes>
                  <loc:openlrFunctionalRoadClass>frc5</loc:openlrFunctionalRoadClass>
                  <loc:openlrFormOfWay>undefined</loc:openlrFormOfWay>
                  <loc:openlrBearing>267</loc:openlrBearing>
                </loc:openlrLineAttributes>
              </loc:openlrLastLocationReferencePoint>
              <loc:openlrOffsets>
                <loc:openlrPositiveOffset>62</loc:openlrPositiveOffset>
                <loc:openlrNegativeOffset>11</loc:openlrNegativeOffset>
              </loc:openlrOffsets>
            </loc:oppositeDirection>
          </loc:openlrLinear>
          <loc:gmlLineString>
            <loc:posList>11.979419257369411 57.870728956501175 11.979088162110786 57.870710736523655</loc:posList>
          </loc:gmlLineString>
        </sit:locationReference>
        <sit:complianceOption>mandatory</sit:complianceOption>
        <sit:roadOrCarriagewayOrLaneManagementType>roadClosed</sit:roadOrCarriagewayOrLaneManagementType>
      </sit:situationRecord>
    </sit:situation>
    <sit:situation id="cecf2fe7-4d15-41c6-8d25-f7b7864c3e31">
      <sit:overallSeverity>low</sit:overallSeverity>
      <sit:situationVersionTime>2025-10-13T08:44:48.027+02:00</sit:situationVersionTime>
      <sit:headerInformation>
        <com:confidentiality>noRestriction</com:confidentiality>
        <com:informationStatus>real</com:informationStatus>
      </sit:headerInformation>
      <sit:situationRecord xsi:type="sit:NonWeatherRelatedRoadConditions" id="SE_STA_TRISSID_1_18837714" version="3">
        <sit:situationRecordCreationTime>2025-10-13T08:44:08.103+02:00</sit:situationRecordCreationTime>
        <sit:situationRecordVersionTime>2025-10-13T08:44:48.027+02:00</sit:situationRecordVersionTime>
        <sit:situationRecordFirstSupplierVersionTime>2025-10-13T08:44:48.027+02:00</sit:situationRecordFirstSupplierVersionTime>
        <sit:probabilityOfOccurrence>certain</sit:probabilityOfOccurrence>
        <sit:severity>low</sit:severity>
        <sit:source>
          <com:sourceName>
            <com:values>
              <com:value lang="sv">Trafikverket</com:value>
            </com:values>
          </com:sourceName>
        </sit:source>
        <sit:validity>
          <com:validityStatus>definedByValidityTimeSpec</com:validityStatus>
          <com:validityTimeSpecification>
            <com:overallStartTime>2025-09-29T09:08:00.000+02:00</com:overallStartTime>
            <com:overallEndTime>2025-10-31T12:00:00.000+01:00</com:overallEndTime>
          </com:validityTimeSpecification>
        </sit:validity>
        <sit:impact>
          <sit:numberOfLanesRestricted>1</sit:numberOfLanesRestricted>
        </sit:impact>
        <sit:generalPublicComment>
          <sit:comment>
            <com:values>
              <com:value lang="sv">Vägskada i höjd med Brotorps kvarn, varningsskyltar utsatta.  Tillfällig hastighetsnedsättning.   </com:value>
            </com:values>
          </sit:comment>
          <sit:commentType>description</sit:commentType>
        </sit:generalPublicComment>
        <sit:locationReference xsi:type="loc:SingleRoadLinearLocation">
          <loc:coordinatesForDisplay>
            <loc:latitude>58.2534</loc:latitude>
            <loc:longitude>13.077093</loc:longitude>
          </loc:coordinatesForDisplay>
          <loc:supplementaryPositionalDescription>
            <loc:lengthAffected>2197</loc:lengthAffected>
            <loc:locationDescription>
              <com:values>
                <com:value lang="sv">Väg 47 från Tråvads kyrka till Brotorps kvarn båda riktningarna i Västra Götalands län (O)</com:value>
              </com:values>
            </loc:locationDescription>
            <loc:carriageway>
              <loc:carriageway>mainCarriageway</loc:carriageway>
            </loc:carriageway>
            <loc:namedArea xsi:type="loc:IsoNamedArea">
              <loc:areaName>
                <com:values>
                  <com:value lang="sv">Saknas</com:value>
                </com:values>
              </loc:areaName>
              <loc:country>SE</loc:country>
              <loc:subdivisionType>county</loc:subdivisionType>
              <loc:subdivisionCode>14</loc:subdivisionCode>
            </loc:namedArea>
            <loc:roadInformation>
              <loc:roadNumber>Väg 47</loc:roadNumber>
            </loc:roadInformation>
          </loc:supplementaryPositionalDescription>
          <loc:openlrLinear>
            <loc:firstDirection>
              <loc:openlrLocationReferencePoint>
                <loc:openlrCoordinates>
                  <loc:latitude>58.245705</loc:latitude>
                  <loc:longitude>13.088774</loc:longitude>
                </loc:openlrCoordinates>
                <loc:openlrLineAttributes>
                  <loc:openlrFunctionalRoadClass>frc1</loc:openlrFunctionalRoadClass>
                  <loc:openlrFormOfWay>undefined</loc:openlrFormOfWay>
                  <loc:openlrBearing>318</loc:openlrBearing>
                </loc:openlrLineAttributes>
                <loc:openlrPathAttributes>
                  <loc:openlrLowestFrcToNextLRPoint>frc1</loc:openlrLowestFrcToNextLRPoint>
                  <loc:openlrDistanceToNextLRPoint>2196</loc:openlrDistanceToNextLRPoint>
                </loc:openlrPathAttributes>
              </loc:openlrLocationReferencePoint>
              <loc:openlrLastLocationReferencePoint>
                <loc:openlrCoordinates>
                  <loc:latitude>58.25889</loc:latitude>
                  <loc:longitude>13.061779</loc:longitude>
                </loc:openlrCoordinates>
                <loc:openlrLineAttributes>
                  <loc:openlrFunctionalRoadClass>frc1</loc:openlrFunctionalRoadClass>
                  <loc:openlrFormOfWay>undefined</loc:openlrFormOfWay>
                  <loc:openlrBearing>131</loc:openlrBearing>
                </loc:openlrLineAttributes>
              </loc:openlrLastLocationReferencePoint>
              <loc:openlrOffsets>
                <loc:openlrPositiveOffset>0</loc:openlrPositiveOffset>
                <loc:openlrNegativeOffset>1</loc:openlrNegativeOffset>
              </loc:openlrOffsets>
            </loc:firstDirection>
            <loc:oppositeDirection>
              <loc:openlrLocationReferencePoint>
                <loc:openlrCoordinates>
                  <loc:latitude>58.25889</loc:latitude>
                  <loc:longitude>13.061779</loc:longitude>
                </loc:openlrCoordinates>
                <loc:openlrLineAttributes>
                  <loc:openlrFunctionalRoadClass>frc1</loc:openlrFunctionalRoadClass>
                  <loc:openlrFormOfWay>undefined</loc:openlrFormOfWay>
                  <loc:openlrBearing>131</loc:openlrBearing>
                </loc:openlrLineAttributes>
                <loc:openlrPathAttributes>
                  <loc:openlrLowestFrcToNextLRPoint>frc1</loc:openlrLowestFrcToNextLRPoint>
                  <loc:openlrDistanceToNextLRPoint>2196</loc:openlrDistanceToNextLRPoint>
                </loc:openlrPathAttributes>
              </loc:openlrLocationReferencePoint>
              <loc:openlrLastLocationReferencePoint>
                <loc:openlrCoordinates>
                  <loc:latitude>58.245705</loc:latitude>
                  <loc:longitude>13.088774</loc:longitude>
                </loc:openlrCoordinates>
                <loc:openlrLineAttributes>
                  <loc:openlrFunctionalRoadClass>frc1</loc:openlrFunctionalRoadClass>
                  <loc:openlrFormOfWay>undefined</loc:openlrFormOfWay>
                  <loc:openlrBearing>318</loc:openlrBearing>
                </loc:openlrLineAttributes>
              </loc:openlrLastLocationReferencePoint>
              <loc:openlrOffsets>
                <loc:openlrPositiveOffset>1</loc:openlrPositiveOffset>
                <loc:openlrNegativeOffset>0</loc:openlrNegativeOffset>
              </loc:openlrOffsets>
            </loc:oppositeDirection>
          </loc:openlrLinear>
          <loc:gmlLineString>
            <loc:posList>13.08877110841113 58.245704637528817 13.086185686591021 58.247214852378711 13.076702853215936 58.253672414985346 13.075210059547169 58.2545466234896 13.07374301560802 58.255221310270692 13.072847327855898 58.2555518893781 13.071285872371588 58.256055327735446 13.065699166160831 58.257451073567623 13.064353916264876 58.257880888585206 13.061778655158044 58.258888304580559</loc:posList>
          </loc:gmlLineString>
          <loc:alertCLinear xsi:type="loc:AlertCMethod4Linear">
            <loc:alertCLocationCountryCode>E</loc:alertCLocationCountryCode>
            <loc:alertCLocationTableNumber>33</loc:alertCLocationTableNumber>
            <loc:alertCLocationTableVersion>2.2</loc:alertCLocationTableVersion>
            <loc:alertCDirection>
              <loc:alertCDirectionCoded>positive</loc:alertCDirectionCoded>
              <loc:alertCAffectedDirection>both</loc:alertCAffectedDirection>
            </loc:alertCDirection>
            <loc:alertCMethod4PrimaryPointLocation>
              <loc:alertCLocation>
                <loc:specificLocation>4105</loc:specificLocation>
              </loc:alertCLocation>
              <loc:offsetDistance>
                <loc:offsetDistance>0</loc:offsetDistance>
              </loc:offsetDistance>
            </loc:alertCMethod4PrimaryPointLocation>
            <loc:alertCMethod4SecondaryPointLocation>
              <loc:alertCLocation>
                <loc:specificLocation>13118</loc:specificLocation>
              </loc:alertCLocation>
              <loc:offsetDistance>
                <loc:offsetDistance>1</loc:offsetDistance>
              </loc:offsetDistance>
            </loc:alertCMethod4SecondaryPointLocation>
          </loc:alertCLinear>
        </sit:locationReference>
        <sit:nonWeatherRelatedRoadConditionType>roadSurfaceInPoorCondition</sit:nonWeatherRelatedRoadConditionType>
      </sit:situationRecord>
    </sit:situation>
    <sit:situation id="74726166-696b-656e-6e75-000000003372">
      <sit:overallSeverity>highest</sit:overallSeverity>
      <sit:situationVersionTime>2025-10-14T10:12:16.440+02:00</sit:situationVersionTime>
      <sit:headerInformation>
        <com:confidentiality>noRestriction</com:confidentiality>
        <com:informationStatus>real</com:informationStatus>
      </sit:headerInformation>
      <sit:situationRecord xsi:type="sit:PublicEvent" id="SE_STA_TRISSID_1_7067521" version="1">
        <sit:situationRecordCreationTime>2025-10-14T10:12:16.440+02:00</sit:situationRecordCreationTime>
        <sit:situationRecordVersionTime>2025-10-14T10:12:16.440+02:00</sit:situationRecordVersionTime>
        <sit:situationRecordFirstSupplierVersionTime>2025-10-14T10:12:16.440+02:00</sit:situationRecordFirstSupplierVersionTime>
        <sit:probabilityOfOccurrence>certain</sit:probabilityOfOccurrence>
        <sit:severity>highest</sit:severity>
        <sit:source>
          <com:sourceName>
            <com:values>
              <com:value lang="sv">Vänersborgs kommun</com:value>
            </com:values>
          </com:sourceName>
        </sit:source>
        <sit:validity>
          <com:validityStatus>definedByValidityTimeSpec</com:validityStatus>
          <com:validityTimeSpecification>
            <com:overallStartTime>2025-10-24T18:00:00.000+02:00</com:overallStartTime>
            <com:overallEndTime>2025-10-25T21:00:00.000+02:00</com:overallEndTime>
          </com:validityTimeSpecification>
        </sit:validity>
        <sit:generalPublicComment>
          <sit:comment>
            <com:values>
              <com:value lang="sv">Drottningatan och Kungsgatan helt avstängda mellan Residensgatan och Vallgatan på grund av den årliga höstmarknaden.</com:value>
            </com:values>
          </sit:comment>
          <sit:commentType>description</sit:commentType>
        </sit:generalPublicComment>
        <sit:locationReference xsi:type="loc:PointLocation">
          <loc:coordinatesForDisplay>
            <loc:latitude>58.380726</loc:latitude>
            <loc:longitude>12.3224125</loc:longitude>
          </loc:coordinatesForDisplay>
          <loc:supplementaryPositionalDescription>
            <loc:locationDescription>
              <com:values>
                <com:value lang="sv">Drottninggatan, Kungsgatan i Vänersborgs kommun i Västra Götalands län, i båda riktningar.</com:value>
              </com:values>
            </loc:locationDescription>
            <loc:carriageway>
              <loc:carriageway>mainCarriageway</loc:carriageway>
            </loc:carriageway>
            <loc:namedArea xsi:type="loc:IsoNamedArea">
              <loc:areaName>
                <com:values>
                  <com:value lang="sv">Saknas</com:value>
                </com:values>
              </loc:areaName>
              <loc:country>SE</loc:country>
              <loc:subdivisionType>county</loc:subdivisionType>
              <loc:subdivisionCode>14</loc:subdivisionCode>
            </loc:namedArea>
            <loc:roadInformation>
              <loc:roadName>Drottninggatan, Kungsgatan</loc:roadName>
            </loc:roadInformation>
          </loc:supplementaryPositionalDescription>
        </sit:locationReference>
        <sit:publicEventType>majorEvent</sit:publicEventType>
      </sit:situationRecord>
      <sit:situationRecord xsi:type="sit:RoadOrCarriagewayOrLaneManagement" id="SE_STA_TRISSID_2_7067521" version="1">
        <sit:situationRecordCreationTime>2025-10-14T10:12:16.440+02:00</sit:situationRecordCreationTime>
        <sit:situationRecordVersionTime>2025-10-14T10:12:16.440+02:00</sit:situationRecordVersionTime>
        <sit:situationRecordFirstSupplierVersionTime>2025-10-14T10:12:16.440+02:00</sit:situationRecordFirstSupplierVersionTime>
        <sit:probabilityOfOccurrence>certain</sit:probabilityOfOccurrence>
        <sit:severity>highest</sit:severity>
        <sit:source>
          <com:sourceName>
            <com:values>
              <com:value lang="sv">Vänersborgs kommun</com:value>
            </com:values>
          </com:sourceName>
        </sit:source>
        <sit:validity>
          <com:validityStatus>definedByValidityTimeSpec</com:validityStatus>
          <com:validityTimeSpecification>
            <com:overallStartTime>2025-10-24T18:00:00.000+02:00</com:overallStartTime>
            <com:overallEndTime>2025-10-25T21:00:00.000+02:00</com:overallEndTime>
          </com:validityTimeSpecification>
        </sit:validity>
        <sit:cause>
          <sit:managedCause>
            <sit:objectReference targetClass="sit:SituationRecord" id="SE_STA_TRISSID_1_7067521" version="0"></sit:objectReference>
          </sit:managedCause>
        </sit:cause>
        <sit:generalPublicComment>
          <sit:comment>
            <com:values>
              <com:value lang="sv">Drottningatan och Kungsgatan helt avstängda mellan Residensgatan och Vallgatan på grund av den årliga höstmarknaden.</com:value>
            </com:values>
          </sit:comment>
          <sit:commentType>description</sit:commentType>
        </sit:generalPublicComment>
        <sit:locationReference xsi:type="loc:PointLocation">
          <loc:coordinatesForDisplay>
            <loc:latitude>58.380726</loc:latitude>
            <loc:longitude>12.3224125</loc:longitude>
          </loc:coordinatesForDisplay>
          <loc:supplementaryPositionalDescription>
            <loc:locationDescription>
              <com:values>
                <com:value lang="sv">Drottninggatan, Kungsgatan i Vänersborgs kommun i Västra Götalands län, i båda riktningar.</com:value>
              </com:values>
            </loc:locationDescription>
            <loc:carriageway>
              <loc:carriageway>mainCarriageway</loc:carriageway>
            </loc:carriageway>
            <loc:namedArea xsi:type="loc:IsoNamedArea">
              <loc:areaName>
                <com:values>
                  <com:value lang="sv">Saknas</com:value>
                </com:values>
              </loc:areaName>
              <loc:country>SE</loc:country>
              <loc:subdivisionType>county</loc:subdivisionType>
              <loc:subdivisionCode>14</loc:subdivisionCode>
            </loc:namedArea>
            <loc:roadInformation>
              <loc:roadName>Drottninggatan, Kungsgatan</loc:roadName>
            </loc:roadInformation>
          </loc:supplementaryPositionalDescription>
        </sit:locationReference>
        <sit:complianceOption>mandatory</sit:complianceOption>
        <sit:roadOrCarriagewayOrLaneManagementType>roadClosed</sit:roadOrCarriagewayOrLaneManagementType>
      </sit:situationRecord>
    </sit:situation>
  </con:payload>
  <con:exchangeInformation modelBaseVersion="3">
    <ex:exchangeContext>
      <ex:codedExchangeProtocol>snapshotPull</ex:codedExchangeProtocol>
      <ex:exchangeSpecificationVersion>Exchange2020</ex:exchangeSpecificationVersion>
      <ex:supplierOrCisRequester>
        <ex:internationalIdentifier>
          <com:country>SE</com:country>
          <com:nationalIdentifier>STA</com:nationalIdentifier>
        </ex:internationalIdentifier>
      </ex:supplierOrCisRequester>
    </ex:exchangeContext>
    <ex:dynamicInformation>
      <ex:exchangeStatus>undefined</ex:exchangeStatus>
      <ex:messageGenerationTimestamp>2025-10-24T13:20:11.000+02:00</ex:messageGenerationTimestamp>
    </ex:dynamicInformation>
  </con:exchangeInformation>
</con:messageContainer>